qwertywertyerty123/__init__.py
qwertywertyerty123/assets.py
qwertywertyerty123/event.py
qwertywertyerty123/hour_counter.py
qwertywertyerty123/main.py
qwertywertyerty123/phase_tracker.py
qwertywertyerty123/pointer.py
qwertywertyerty123/sandbox.py
qwertywertyerty123/application/__init__.py
qwertywertyerty123/application/config.py
qwertywertyerty123/demos/__init__.py
qwertywertyerty123/log/__init__.py
qwertywertyerty123/log/logger.py
qwertywertyerty12-1.0.0.dist-info/LICENSE
qwertywertyerty12-1.0.0.dist-info/METADATA
qwertywertyerty12-1.0.0.dist-info/WHEEL
qwertywertyerty12-1.0.0.dist-info/top_level.txt
qwertywertyerty12-1.0.0.dist-info/RECORD
