Metadata-Version: 2.1
Name: qwertywertyerty12
Version: 1.0.0
Summary: A discrete event simulator
Home-page: https://github.com/darrenkhlim/qwertywertyerty12
Author: NUS
Author-email: e0426117@u.nus.edu
License: NUS
Platform: UNKNOWN
